AUTHORS
LICENSE
MANIFEST.in
README.rst
setup.py
jdhp_setuptools_demo/__init__.py
jdhp_setuptools_demo/row_your_boat.py
jdhp_setuptools_demo.egg-info/PKG-INFO
jdhp_setuptools_demo.egg-info/SOURCES.txt
jdhp_setuptools_demo.egg-info/dependency_links.txt
jdhp_setuptools_demo.egg-info/entry_points.txt
jdhp_setuptools_demo.egg-info/top_level.txt